waymo_open_dataset_tf_2_0_0-1.3.1.dist-info/METADATA
waymo_open_dataset_tf_2_0_0-1.3.1.dist-info/top_level.txt
waymo_open_dataset_tf_2_0_0-1.3.1.dist-info/LICENSE
waymo_open_dataset_tf_2_0_0-1.3.1.dist-info/RECORD
waymo_open_dataset_tf_2_0_0-1.3.1.dist-info/WHEEL
waymo_open_dataset/libdataset_cc_proto.so
waymo_open_dataset/dataset_pb2.py
waymo_open_dataset/__init__.py
waymo_open_dataset/label_pb2.py
waymo_open_dataset/liblabel_cc_proto.so
waymo_open_dataset/protos/submission_pb2.py
waymo_open_dataset/protos/libsubmission_cc_proto.so
waymo_open_dataset/protos/metrics_pb2.py
waymo_open_dataset/protos/libmetrics_cc_proto.so
waymo_open_dataset/protos/map_pb2.py
waymo_open_dataset/protos/motion_metrics_pb2.py
waymo_open_dataset/protos/breakdown_pb2.py
waymo_open_dataset/protos/motion_submission_pb2.py
waymo_open_dataset/protos/libmotion_metrics_cc_proto.so
waymo_open_dataset/protos/__init__.py
waymo_open_dataset/protos/libmotion_submission_cc_proto.so
waymo_open_dataset/protos/libbreakdown_cc_proto.so
waymo_open_dataset/protos/libmap_cc_proto.so
waymo_open_dataset/protos/scenario_pb2.py
waymo_open_dataset/protos/libscenario_cc_proto.so
waymo_open_dataset/math/libpolygon2d.so
waymo_open_dataset/math/libsegment2d.so
waymo_open_dataset/math/libexactfloat.so
waymo_open_dataset/math/libbox2d.so
waymo_open_dataset/camera/libcamera_model.so
waymo_open_dataset/camera/ops/camera_model_ops.so
waymo_open_dataset/common/libstatus.so
waymo_open_dataset/metrics/libhungarian.so
waymo_open_dataset/metrics/libbreakdown_generator.so
waymo_open_dataset/metrics/libmotion_metrics_utils.so
waymo_open_dataset/metrics/libmot.so
waymo_open_dataset/metrics/libmatcher.so
waymo_open_dataset/metrics/libconfig_util.so
waymo_open_dataset/metrics/libmotion_metrics.so
waymo_open_dataset/metrics/libmetrics_utils.so
waymo_open_dataset/metrics/__init__.py
waymo_open_dataset/metrics/libtracking_metrics.so
waymo_open_dataset/metrics/libdetection_metrics.so
waymo_open_dataset/metrics/libiou.so
waymo_open_dataset/metrics/libtest_utils.so
waymo_open_dataset/metrics/ops/py_metrics_ops.py
waymo_open_dataset/metrics/ops/libutils.so
waymo_open_dataset/metrics/ops/metrics_ops.so
waymo_open_dataset/metrics/ops/__init__.py
