Metadata-Version: 2.1
Name: waymo-open-dataset-tf-2-0-0
Version: 1.3.1
Summary: Waymo Open Dataset libraries.
Home-page: https://waymo.com/open
Author: Waymo Open Dataset Authors
Author-email: waymo-open-dataset@google.com
License: Apache 2.0
Keywords: autonomous driving dataset machine learning
Platform: UNKNOWN
Classifier: Development Status :: 5 - Production/Stable
Classifier: Intended Audience :: Developers
Classifier: Intended Audience :: Education
Classifier: Intended Audience :: Science/Research
Classifier: License :: OSI Approved :: Apache Software License
Classifier: Programming Language :: Python :: 3.6
Classifier: Programming Language :: Python :: 3.7
Classifier: Programming Language :: Python :: 3.8
Classifier: Topic :: Scientific/Engineering
Classifier: Topic :: Scientific/Engineering :: Artificial Intelligence
Classifier: Topic :: Software Development
Classifier: Topic :: Software Development :: Libraries
Classifier: Topic :: Software Development :: Libraries :: Python Modules
Requires-Python: >=3
Requires-Dist: tensorflow-gpu (==2.0.0)
